{"backdrops":[{"aspect_ratio":1.778,"height":1080,"iso_639_1":"fr","file_path":"/4udTK6mZ8zR2aCE0b0spddWWzMZ.jpg","vote_average":5.322,"vote_count":5,"width":1920}],"id":426,"logos":[{"aspect_ratio":4.322,"height":115,"iso_639_1":"fr","file_path":"/kUHA991IGtL81G0wA4QuNAC2NhC.png","vote_average":0.0,"vote_count":0,"width":497}],"posters":[{"aspect_ratio":0.667,"height":1500,"iso_639_1":"fr","file_path":"/uFhTTIJypI747dfXpTmsqCxZgZB.jpg","vote_average":5.326,"vote_count":7,"width":1000},{"aspect_ratio":0.667,"height":3000,"iso_639_1":"fr","file_path":"/pk12ikPchJXzOpiqhdmGcxSuscQ.jpg","vote_average":5.312,"vote_count":1,"width":2000},{"aspect_ratio":0.667,"height":3000,"iso_639_1":"fr","file_path":"/hkhbbSQdsV3U0HtuPugHfx2wOi9.jpg","vote_average":5.264,"vote_count":8,"width":2000},{"aspect_ratio":0.667,"height":3000,"iso_639_1":"fr","file_path":"/qmwm27Lwpl5TGzMIq2hc6CxBDQa.jpg","vote_average":5.252,"vote_count":4,"width":2000},{"aspect_ratio":0.667,"height":1500,"iso_639_1":"fr","file_path":"/zJBPRM7NRJyoVQtiyDX1qN48Qsf.jpg","vote_average":5.18,"vote_count":3,"width":1000},{"aspect_ratio":0.667,"height":750,"iso_639_1":"fr","file_path":"/sUBy9uUfofQ7erqK9JPkIFmK9Bc.jpg","vote_average":5.172,"vote_count":1,"width":500},{"aspect_ratio":0.667,"height":3000,"iso_639_1":"fr","file_path":"/shkxYaYV1spBG8KsXjxMvQybZOx.jpg","vote_average":5.172,"vote_count":1,"width":2000},{"aspect_ratio":0.667,"height":750,"iso_639_1":"fr","file_path":"/krlJyAgdyY59Yue6QxodwCFBqMt.jpg","vote_average":5.044,"vote_count":3,"width":500}]}