{"backdrops":[{"aspect_ratio":1.778,"height":1080,"iso_639_1":"fr","file_path":"/uyz2XvT2etFUg2t96vY4LKINgQf.jpg","vote_average":5.312,"vote_count":1,"width":1920}],"id":668,"logos":[{"aspect_ratio":2.659,"height":296,"iso_639_1":"fr","file_path":"/8a9p7UdKYxazXRi90PScceq2WiR.png","vote_average":0.0,"vote_count":0,"width":787}],"posters":[{"aspect_ratio":0.667,"height":1500,"iso_639_1":"fr","file_path":"/sHYTFChLjBU7TLQwpcX5BHQNUp9.jpg","vote_average":5.322,"vote_count":5,"width":1000},{"aspect_ratio":0.667,"height":3000,"iso_639_1":"fr","file_path":"/u1yugkv69TUP5NLuOn2IyF40hpG.jpg","vote_average":5.19,"vote_count":5,"width":2000},{"aspect_ratio":0.667,"height":750,"iso_639_1":"fr","file_path":"/5kWESo6r2cWQtRFDsk2TUx9quzQ.jpg","vote_average":5.172,"vote_count":1,"width":500},{"aspect_ratio":0.667,"height":1500,"iso_639_1":"fr","file_path":"/vqoX9Lj115kJztulLjqHidjtWcq.jpg","vote_average":5.128,"vote_count":6,"width":1000},{"aspect_ratio":0.667,"height":3000,"iso_639_1":"fr","file_path":"/6oQP7BdT79JLj45jalQk6RoKT9w.jpg","vote_average":5.118,"vote_count":4,"width":2000},{"aspect_ratio":0.667,"height":750,"iso_639_1":"fr","file_path":"/3zHYITea1nlv9jSb3BwTUvGVX9Q.jpg","vote_average":5.106,"vote_count":2,"width":500},{"aspect_ratio":0.667,"height":900,"iso_639_1":"fr","file_path":"/jopMjHa0R0BwjzPWOqPiizgtbq2.jpg","vote_average":5.106,"vote_count":2,"width":600},{"aspect_ratio":0.667,"height":1500,"iso_639_1":"fr","file_path":"/6wbnOn1lYk7KoRR1BxfI7NEM7Ch.jpg","vote_average":5.106,"vote_count":2,"width":1000},{"aspect_ratio":0.667,"height":1491,"iso_639_1":"fr","file_path":"/8E9uguBrIW7A8YyGrotAVwCmzcF.jpg","vote_average":5.106,"vote_count":2,"width":994},{"aspect_ratio":0.667,"height":3000,"iso_639_1":"fr","file_path":"/bnBOmrW8dV0aZF8xc4SrOZJtOO2.jpg","vote_average":5.106,"vote_count":2,"width":2000},{"aspect_ratio":0.667,"height":1497,"iso_639_1":"fr","file_path":"/kIXvbY619TFLWCLYfI8YETo0uy3.jpg","vote_average":5.106,"vote_count":2,"width":998},{"aspect_ratio":0.667,"height":1497,"iso_639_1":"fr","file_path":"/q44KQyb6ZcfUPAZILBXZNiArsqS.jpg","vote_average":5.106,"vote_count":2,"width":998},{"aspect_ratio":0.667,"height":1000,"iso_639_1":"fr","file_path":"/AnW8mo1g8UK0LZ5fdJoWIZ8Bsam.jpg","vote_average":5.056,"vote_count":5,"width":667},{"aspect_ratio":0.667,"height":1500,"iso_639_1":"fr","file_path":"/bwIyzvPRRgLs11qpYp9RBv8gfeu.jpg","vote_average":0.0,"vote_count":0,"width":1000}]}