{"backdrops":[],"id":698,"logos":[{"aspect_ratio":2.842,"height":260,"iso_639_1":"fr","file_path":"/rQ6I8SmXqBadRJcEMoVH598qS0P.png","vote_average":0.0,"vote_count":0,"width":739}],"posters":[{"aspect_ratio":0.737,"height":1754,"iso_639_1":"fr","file_path":"/vF11JtjH1PmEvsRo4djEWWmHXvi.jpg","vote_average":5.33,"vote_count":9,"width":1292},{"aspect_ratio":0.667,"height":750,"iso_639_1":"fr","file_path":"/mpcRE1eAFtCTqxyqGiT4MQnkhD6.jpg","vote_average":5.246,"vote_count":2,"width":500},{"aspect_ratio":0.667,"height":1500,"iso_639_1":"fr","file_path":"/wMBq5FtHLESNZcBwlDCxIbCWZSB.jpg","vote_average":5.128,"vote_count":6,"width":1000},{"aspect_ratio":0.667,"height":1500,"iso_639_1":"fr","file_path":"/3rZgmjFV5SdDvu3H4o82XuoO35i.jpg","vote_average":4.982,"vote_count":4,"width":1000},{"aspect_ratio":0.667,"height":1500,"iso_639_1":"fr","file_path":"/6PiKoMHTEzjCd5LJgI1n6lmcmCL.jpg","vote_average":0.0,"vote_count":0,"width":1000}]}