{"backdrops":[],"id":979,"logos":[{"aspect_ratio":6.174,"height":207,"iso_639_1":"fr","file_path":"/gbyaHQczNSJZZPzQlYoHW8Zd3Dq.png","vote_average":0.0,"vote_count":0,"width":1278}],"posters":[{"aspect_ratio":0.667,"height":1500,"iso_639_1":"fr","file_path":"/o6bXnLTiNUvnHShkxqUOnzpdCgk.jpg","vote_average":5.518,"vote_count":10,"width":1000},{"aspect_ratio":0.667,"height":3000,"iso_639_1":"fr","file_path":"/ne31Fq4h1UhIoS2o17JrICrEBrT.jpg","vote_average":5.454,"vote_count":3,"width":2000},{"aspect_ratio":0.667,"height":3000,"iso_639_1":"fr","file_path":"/hdUVu62nTtUIw9v6XNckAupsSQA.jpg","vote_average":5.388,"vote_count":4,"width":2000},{"aspect_ratio":0.667,"height":3000,"iso_639_1":"fr","file_path":"/AdrItykbv1evqcbIPrItVWnkaKj.jpg","vote_average":5.318,"vote_count":3,"width":2000},{"aspect_ratio":0.667,"height":3000,"iso_639_1":"fr","file_path":"/yYk0GhFIKii1ZUgpEmV2vFV43Ah.jpg","vote_average":5.246,"vote_count":2,"width":2000},{"aspect_ratio":0.667,"height":2160,"iso_639_1":"fr","file_path":"/o5pB4ui1cXj4tHdSlFpEQ0vN9AW.jpg","vote_average":0.0,"vote_count":0,"width":1440},{"aspect_ratio":0.667,"height":1500,"iso_639_1":"fr","file_path":"/7PSSlrTvdmz8DjWZrArZ6zaMkAw.jpg","vote_average":0.0,"vote_count":0,"width":1000}]}