{"adult":false,"backdrop_path":"/5bzPWQ2dFUl2aZKkp7ILJVVkRed.jpg","belongs_to_collection":{"id":264,"name":"Retour vers le futur - Saga","poster_path":"/nykumUbCw1o43fHGkRqj9hO2c2h.jpg","backdrop_path":"/AqQotqj7XOI6GjB28nhMMa8YzOT.jpg"},"budget":19000000,"genres":[{"id":12,"name":"Aventure"},{"id":35,"name":"Comédie"},{"id":878,"name":"Science-Fiction"}],"homepage":"","id":105,"imdb_id":"tt0088763","original_language":"en","original_title":"Back to the Future","overview":"Marty Mc Fly est un adolescent américain des années 80 : il va au lycée, aime le Rock, fait du skate-board… Mais il est aussi l'ami d'un savant excentrique, le Dr Emmet Brown, inventeur d'une machine à remonter le temps très particulière, une DeLorean. Marty se retrouve propulsé par hasard en 1955, à une époque où il n'était même pas né. Avant d'entreprendre son voyage de retour vers le futur, il va devoir s'assurer que ses parents, encore étudiants, se rencontrent… et se marient !!!","popularity":69.131,"poster_path":"/y9bs2N5rEM51YBXbU7N5PaXJc6W.jpg","production_companies":[{"id":33,"logo_path":"/8lvHyhjr8oUKOOy2dKXoALWKdp0.png","name":"Universal Pictures","origin_country":"US"},{"id":56,"logo_path":"/cEaxANEisCqeEoRvODv2dO1I0iI.png","name":"Amblin Entertainment","origin_country":"US"}],"production_countries":[{"iso_3166_1":"US","name":"United States of America"}],"release_date":"1985-07-03","revenue":381109762,"runtime":116,"spoken_languages":[{"english_name":"English","iso_639_1":"en","name":"English"}],"status":"Released","tagline":"Jamais à temps à l’école, jamais à temps à la maison, un jour il se retrouve complètement hors du temps…","title":"Retour vers le futur","video":false,"vote_average":8.307,"vote_count":17183}