{"adult":false,"backdrop_path":"/6hA8eN37Ky8C6X6uJwKsBNTuj4t.jpg","belongs_to_collection":null,"budget":12899867,"genres":[{"id":35,"name":"Comédie"},{"id":18,"name":"Drame"},{"id":10749,"name":"Romance"}],"homepage":"","id":219,"imdb_id":"tt0441909","original_language":"es","original_title":"Volver","overview":"Madrid et les quartiers effervescents de la classe ouvrière, où les immigrés des différentes provinces espagnoles partagent leurs rêves, leur vie et leur fortune avec une multitude d'ethnies étrangères. Au sein de cette trame sociale, trois générations de femmes survivent au vent, au feu, et même à la mort, grâce à leur bonté, à leur audace et à une vitalité sans limites.","popularity":17.587,"poster_path":"/bkO47UpJxlTORkgE3QdMo1eor8f.jpg","production_companies":[{"id":49,"logo_path":"/xpf5iHdvvBtsH8jBMlgIJHAET0c.png","name":"El Deseo","origin_country":"ES"},{"id":981,"logo_path":"/pkrdO9ykplO4Zc8edikoSX5APUN.png","name":"TVE","origin_country":"ES"},{"id":9335,"logo_path":null,"name":"Canal+ España","origin_country":"ES"},{"id":29258,"logo_path":null,"name":"Ministerio de Cultura España","origin_country":""}],"production_countries":[{"iso_3166_1":"ES","name":"Spain"}],"release_date":"2006-03-17","revenue":85582407,"runtime":121,"spoken_languages":[{"english_name":"Spanish","iso_639_1":"es","name":"Español"}],"status":"Released","tagline":"","title":"Volver","video":false,"vote_average":7.467,"vote_count":1422}