{"adult":false,"backdrop_path":"/1K9YJzQ6r5nCrOVrjSnAmji8zLc.jpg","belongs_to_collection":null,"budget":0,"genres":[{"id":18,"name":"Drame"}],"homepage":"","id":233,"imdb_id":"tt0080117","original_language":"en","original_title":"The Wanderers","overview":"Les années 1960, à New York, dans le Bronx. L'histoire décrit la vie quotidienne de jeunes qui se regroupent en bandes, chacune avec ses codes, vestimentaires ou physiques. Entre les rencontres avec les filles, les rivalités entre bandes, les problèmes ethniques, on découvre la vie de ces jeunes qui vont bientôt faire leurs premiers pas dans la vie d'adultes.","popularity":10.683,"poster_path":"/6d4aCQJIfQiMMtg3lpOSX2hihBH.jpg","production_companies":[{"id":41,"logo_path":"/xAot4SSOIHiWQ2WEnVXYGR1lce9.png","name":"Orion Pictures","origin_country":"US"},{"id":14772,"logo_path":"/1XTIrcpK2JgnKn1RYgsPEJiUO0k.png","name":"Warner Bros. Home Entertainment Group","origin_country":"US"}],"production_countries":[{"iso_3166_1":"US","name":"United States of America"}],"release_date":"1979-07-13","revenue":23000000,"runtime":117,"spoken_languages":[{"english_name":"English","iso_639_1":"en","name":"English"}],"status":"Released","tagline":"","title":"Les Seigneurs","video":false,"vote_average":7.0,"vote_count":149}