{"adult":false,"backdrop_path":"/1qwXItFKqvKYyW1CwbYhxyUC8Pj.jpg","belongs_to_collection":null,"budget":0,"genres":[{"id":18,"name":"Drame"},{"id":36,"name":"Histoire"},{"id":10749,"name":"Romance"},{"id":35,"name":"Comédie"}],"homepage":"","id":554,"imdb_id":"tt0308476","original_language":"ru","original_title":"Кукушка","overview":"Septembre 1944, le Finlandais Veiko est enchaîner par ses camarades à un rocher et abandonné à son sort. Dans le camp de l'Armée Rouge un capitaine est transporté sous surveillance au Quartier Général pour des propos anti-soviétiques. Tandis que Veiko réussit à se libérer, le convoi des russes et attaqué. Seul le capitaine survit et est emmené par Anni, une femme lapone, dans sa demeure pour y être soigné.  Veiko trouve refuge dans la ferme de Anni et entre les trois va commencer une cohabitation difficile. Personne ne comprend la langue de l'autre, or Anni, qui a perdu son mari, remarque que sa solitude a pris fin. Elle s'emploie à séduire avec culot les deux hommes arrivés miraculeusement chez elle.","popularity":3.619,"poster_path":"/i21z0FHES4Uh3zDnzYyFLZN2AB7.jpg","production_companies":[{"id":318,"logo_path":"/q0UG4oZERwIywJdDPF4lRlvdYGW.png","name":"CTB Film Company","origin_country":"RU"}],"production_countries":[{"iso_3166_1":"FI","name":"Finland"},{"iso_3166_1":"RU","name":"Russia"}],"release_date":"2002-01-01","revenue":0,"runtime":99,"spoken_languages":[{"english_name":"German","iso_639_1":"de","name":"Deutsch"},{"english_name":"Russian","iso_639_1":"ru","name":"Pусский"},{"english_name":"Finnish","iso_639_1":"fi","name":"suomi"}],"status":"Released","tagline":"","title":"Kukushka, le coucou","video":false,"vote_average":7.045,"vote_count":66}