{"adult":false,"backdrop_path":"/liZhDhrrNVX8IK4TaeaFodzMamy.jpg","belongs_to_collection":null,"budget":3000000,"genres":[{"id":18,"name":"Drame"},{"id":36,"name":"Histoire"},{"id":10752,"name":"Guerre"}],"homepage":"","id":826,"imdb_id":"tt0050212","original_language":"en","original_title":"The Bridge on the River Kwai","overview":"En 1943, le colonel Saïto dirige un camp de prisonniers dans la jungle birmane. Il reçoit l’ordre de construire un pont sur la rivière Kwaï et d’y faire travailler les détenus, y compris les officiers, au mépris des conventions internationales. Le colonel anglais Nicholson, capturé à Singapour avec ses troupes, refuse énergiquement de participer au chantier. Saïto pense pouvoir le faire plier en le soumettant à toutes sortes de vexations et de sévices, mais Nicholson tient bon. Son geôlier finit par céder. Nicholson accepte alors, de son plein gré, de prendre la tête des opérations pour montrer aux Japonais de quoi sont capables les soldats de Sa Majesté. Pendant ce temps, un commando américain progresse prudemment vers le site, dans le but de faire sauter l’ouvrage…","popularity":17.264,"poster_path":"/lbqfOiggULL8qRdZ9403VWx1PbD.jpg","production_companies":[{"id":5,"logo_path":"/lieeAioEBVsgsoDT9HICrdt5iRa.png","name":"Columbia Pictures","origin_country":"US"},{"id":11356,"logo_path":null,"name":"Horizon Pictures","origin_country":"GB"}],"production_countries":[{"iso_3166_1":"GB","name":"United Kingdom"},{"iso_3166_1":"US","name":"United States of America"}],"release_date":"1957-10-11","revenue":44908000,"runtime":160,"spoken_languages":[{"english_name":"Japanese","iso_639_1":"ja","name":"日本語"},{"english_name":"Thai","iso_639_1":"th","name":"ภาษาไทย"},{"english_name":"English","iso_639_1":"en","name":"English"}],"status":"Released","tagline":"","title":"Le Pont de la rivière Kwaï","video":false,"vote_average":7.819,"vote_count":1666}