{"adult":false,"backdrop_path":"/yEasywTxSzxXcFQKnYMMPOUSgdS.jpg","belongs_to_collection":null,"budget":0,"genres":[{"id":35,"name":"Comédie"},{"id":18,"name":"Drame"}],"homepage":"","id":906,"imdb_id":"tt0020842","original_language":"de","original_title":"Die Drei von der Tankstelle","overview":"Trois amis reviennent d'un voyage. Completement demunis, ils vendent leur voiture et ouvrent une station essence qui marche bien. Leur cliente la plus fidele est Liliane dont chacun tombe amoureux.","popularity":1.852,"poster_path":"/7JMa5tn9zdA6rwrU8qbslhEBGWU.jpg","production_companies":[{"id":12372,"logo_path":null,"name":"UFA","origin_country":"DE"}],"production_countries":[{"iso_3166_1":"DE","name":"Germany"}],"release_date":"1930-09-15","revenue":0,"runtime":90,"spoken_languages":[{"english_name":"German","iso_639_1":"de","name":"Deutsch"}],"status":"Released","tagline":"","title":"Le chemin du paradis","video":false,"vote_average":6.235,"vote_count":17}