{"id":160,"cast":[{"adult":false,"gender":0,"id":1419407,"known_for_department":"Acting","name":"Madeleine Koehler","original_name":"Madeleine Koehler","popularity":0.84,"profile_path":null,"cast_id":10,"character":"Self","credit_id":"5e3a557e43250f0015c693ff","order":0},{"adult":false,"gender":0,"id":1419405,"known_for_department":"Acting","name":"Marcel Koehler","original_name":"Marcel Koehler","popularity":0.6,"profile_path":null,"cast_id":11,"character":"Self","credit_id":"5e3a558dac8e6b0015c91a03","order":1},{"adult":false,"gender":1,"id":1942346,"known_for_department":"Acting","name":"Mrs. Auguste Lumière","original_name":"Mrs. Auguste Lumière","popularity":1.396,"profile_path":"/2S8jynN8fCeO1rQ6dPfeWVuhvs7.jpg","cast_id":12,"character":"Self","credit_id":"5e3a559e0c2710001375342d","order":2},{"adult":false,"gender":0,"id":1419617,"known_for_department":"Acting","name":"Jeanne-Joséphine Lumière","original_name":"Jeanne-Joséphine Lumière","popularity":0.694,"profile_path":null,"cast_id":13,"character":"Self","credit_id":"5e3a55aaac8e6b0011c97510","order":3},{"adult":false,"gender":0,"id":1419400,"known_for_department":"Acting","name":"Rose Lumière","original_name":"Rose Lumière","popularity":1.96,"profile_path":null,"cast_id":14,"character":"Self","credit_id":"5e3a55b6ac8e6b0011c97565","order":4},{"adult":false,"gender":0,"id":1419409,"known_for_department":"Acting","name":"Suzanne Lumière","original_name":"Suzanne Lumière","popularity":0.6,"profile_path":null,"cast_id":15,"character":"Self","credit_id":"5e3a55c343250f0015c694ff","order":5}],"crew":[{"adult":false,"gender":2,"id":1867,"known_for_department":"Production","name":"Auguste Lumière","original_name":"Auguste Lumière","popularity":1.932,"profile_path":"/qHd5Fodx9NzCFlAxAGLM9gFQ2Z7.jpg","credit_id":"56651844c3a3685118000fcc","department":"Directing","job":"Director"},{"adult":false,"gender":2,"id":1867,"known_for_department":"Production","name":"Auguste Lumière","original_name":"Auguste Lumière","popularity":1.932,"profile_path":"/qHd5Fodx9NzCFlAxAGLM9gFQ2Z7.jpg","credit_id":"5e3a5562ac8e6b001ac8f130","department":"Production","job":"Producer"},{"adult":false,"gender":2,"id":1868,"known_for_department":"Directing","name":"Louis Lumière","original_name":"Louis Lumière","popularity":1.214,"profile_path":"/vPtoLsFHSDtqkC3oQiFrLWE7Eyw.jpg","credit_id":"54d0fb38c3a3680f37001adf","department":"Directing","job":"Director"},{"adult":false,"gender":2,"id":1868,"known_for_department":"Directing","name":"Louis Lumière","original_name":"Louis Lumière","popularity":1.214,"profile_path":"/vPtoLsFHSDtqkC3oQiFrLWE7Eyw.jpg","credit_id":"61056e954f33ad0045409912","department":"Camera","job":"Director of Photography"},{"adult":false,"gender":2,"id":1868,"known_for_department":"Directing","name":"Louis Lumière","original_name":"Louis Lumière","popularity":1.214,"profile_path":"/vPtoLsFHSDtqkC3oQiFrLWE7Eyw.jpg","credit_id":"5e3a555a98f1f1001809ca6d","department":"Production","job":"Producer"}]}