{"id":942,"cast":[{"adult":false,"gender":2,"id":2461,"known_for_department":"Acting","name":"Mel Gibson","original_name":"Mel Gibson","popularity":45.921,"profile_path":"/oSOYCghY3XcXBYqMA0fsEi8WKaa.jpg","cast_id":18,"character":"Martin Riggs","credit_id":"52fe4291c3a36847f8028c21","order":0},{"adult":false,"gender":2,"id":2047,"known_for_department":"Acting","name":"Danny Glover","original_name":"Danny Glover","popularity":12.156,"profile_path":"/whWpsKpF96i5nrQK98zBHGmuBR2.jpg","cast_id":19,"character":"Roger Murtaugh","credit_id":"52fe4291c3a36847f8028c25","order":1},{"adult":false,"gender":2,"id":4517,"known_for_department":"Acting","name":"Joe Pesci","original_name":"Joe Pesci","popularity":26.221,"profile_path":"/4AO0Rwdg2ky8Usmgzgj0dvhy7Zw.jpg","cast_id":20,"character":"Leo Getz","credit_id":"52fe4291c3a36847f8028c29","order":2},{"adult":false,"gender":2,"id":14324,"known_for_department":"Acting","name":"Joss Ackland","original_name":"Joss Ackland","popularity":5.145,"profile_path":"/k8GQrf54DLILcLBmnMq94xijA6z.jpg","cast_id":21,"character":"Arjen Rudd","credit_id":"52fe4291c3a36847f8028c2d","order":3},{"adult":false,"gender":2,"id":14325,"known_for_department":"Acting","name":"Derrick O'Connor","original_name":"Derrick O'Connor","popularity":2.682,"profile_path":"/ujw2zrsPldMXgIXeXIEnCBBOw1o.jpg","cast_id":22,"character":"Pieter 'Adolph' Vorstedt","credit_id":"52fe4291c3a36847f8028c31","order":4},{"adult":false,"gender":1,"id":14326,"known_for_department":"Acting","name":"Patsy Kensit","original_name":"Patsy Kensit","popularity":12.305,"profile_path":"/r60KQk3xOmMIhGmJqCeHQq6RX68.jpg","cast_id":23,"character":"Rika van den Haas","credit_id":"52fe4291c3a36847f8028c35","order":5},{"adult":false,"gender":1,"id":14313,"known_for_department":"Acting","name":"Darlene Love","original_name":"Darlene Love","popularity":3.905,"profile_path":"/5V7j58GBnRmpiEIZQlT7AXHErKy.jpg","cast_id":24,"character":"Trish Murtaugh","credit_id":"52fe4291c3a36847f8028c39","order":6},{"adult":false,"gender":2,"id":14328,"known_for_department":"Acting","name":"Steve Kahan","original_name":"Steve Kahan","popularity":5.501,"profile_path":"/clyTGAxNCmF0BxhnaZxbWDz7skt.jpg","cast_id":25,"character":"Captain Ed Murphy","credit_id":"52fe4291c3a36847f8028c3d","order":7},{"adult":false,"gender":2,"id":6576,"known_for_department":"Acting","name":"Mark Rolston","original_name":"Mark Rolston","popularity":7.083,"profile_path":"/hcrNRIptYMRXgkJ9k76BlQu6DQp.jpg","cast_id":26,"character":"Hans","credit_id":"52fe4291c3a36847f8028c41","order":8},{"adult":false,"gender":1,"id":3981,"known_for_department":"Acting","name":"Jenette Goldstein","original_name":"Jenette Goldstein","popularity":6.974,"profile_path":"/rIDF2017eiY1HxPwXnXW24rv66o.jpg","cast_id":27,"character":"Officer Meagan Shapiro","credit_id":"52fe4291c3a36847f8028c45","order":9},{"adult":false,"gender":2,"id":14329,"known_for_department":"Acting","name":"Dean Norris","original_name":"Dean Norris","popularity":20.457,"profile_path":"/yV3DZ52LYRf5F605xRas5BEcJrZ.jpg","cast_id":28,"character":"Tim Cavanaugh","credit_id":"52fe4291c3a36847f8028c49","order":10},{"adult":false,"gender":2,"id":14330,"known_for_department":"Acting","name":"Juney Smith","original_name":"Juney Smith","popularity":2.58,"profile_path":"/3mmiJBLtxZTsP4AMzOSQbcccV3D.jpg","cast_id":29,"character":"Tom Wyler","credit_id":"52fe4291c3a36847f8028c4d","order":11},{"adult":false,"gender":2,"id":14331,"known_for_department":"Acting","name":"Nestor Serrano","original_name":"Nestor Serrano","popularity":8.045,"profile_path":"/eHc35FzO1EfoyqYa1YQ67snfEnR.jpg","cast_id":30,"character":"Eddie Estaban","credit_id":"52fe4291c3a36847f8028c51","order":12},{"adult":false,"gender":2,"id":14332,"known_for_department":"Acting","name":"Philip Suriano","original_name":"Philip Suriano","popularity":2.356,"profile_path":null,"cast_id":31,"character":"Joseph Ragucci","credit_id":"52fe4291c3a36847f8028c55","order":13},{"adult":false,"gender":2,"id":14333,"known_for_department":"Acting","name":"Grand L. Bush","original_name":"Grand L. Bush","popularity":5.499,"profile_path":"/iebc00VeSoRkzkvB5D35hTBbFxa.jpg","cast_id":32,"character":"Jerry Collins","credit_id":"52fe4291c3a36847f8028c59","order":14},{"adult":false,"gender":2,"id":14334,"known_for_department":"Acting","name":"Allan Dean Moore","original_name":"Allan Dean Moore","popularity":0.84,"profile_path":null,"cast_id":33,"character":"George","credit_id":"52fe4291c3a36847f8028c5d","order":15},{"adult":false,"gender":2,"id":10489,"known_for_department":"Acting","name":"Jack McGee","original_name":"Jack McGee","popularity":4.842,"profile_path":"/xzBLwEdWxxZbZ3qbGrddldXvnSS.jpg","cast_id":34,"character":"Mickey McGee, the Carpenter","credit_id":"52fe4291c3a36847f8028c61","order":16},{"adult":false,"gender":1,"id":23967,"known_for_department":"Acting","name":"Mary Ellen Trainor","original_name":"Mary Ellen Trainor","popularity":6.866,"profile_path":"/Y926jxSOXikBiqQIptho1VzU9o.jpg","cast_id":36,"character":"Police Psychiatrist","credit_id":"52fe4291c3a36847f8028c6b","order":17},{"adult":false,"gender":1,"id":14314,"known_for_department":"Acting","name":"Traci Wolfe","original_name":"Traci Wolfe","popularity":3.998,"profile_path":"/lvPqdsmm3nYO9xjdH1e9kAMrsdo.jpg","cast_id":42,"character":"Rianne Murtaugh","credit_id":"58740336c3a368174c013702","order":18},{"adult":false,"gender":1,"id":14317,"known_for_department":"Acting","name":"Ebonie Smith","original_name":"Ebonie Smith","popularity":10.328,"profile_path":"/itJRhpA4qfkdYvtpfgWc5xRatHX.jpg","cast_id":43,"character":"Carrie Murtaugh","credit_id":"58748705c3a368066a0025e7","order":19},{"adult":false,"gender":2,"id":14316,"known_for_department":"Acting","name":"Damon Hines","original_name":"Damon Hines","popularity":9.408,"profile_path":"/lRAPiS5bAORffiQ8gHmEmP14ww7.jpg","cast_id":44,"character":"Nick Murtaugh","credit_id":"587488b79251414494002556","order":20},{"adult":false,"gender":2,"id":1785660,"known_for_department":"Acting","name":"Tony Carreiro","original_name":"Tony Carreiro","popularity":2.88,"profile_path":"/sorvm0Ro6X21JnseilG2TLw2qVk.jpg","cast_id":107,"character":"Marcelli","credit_id":"5ee491f4a217c0001fd09733","order":21},{"adult":false,"gender":2,"id":54859,"known_for_department":"Acting","name":"Sherman Howard","original_name":"Sherman Howard","popularity":4.999,"profile_path":"/oaFzlV0kddSSSelh4VSIJaKt7Gf.jpg","cast_id":108,"character":"Hitman","credit_id":"5ee492205b4fed0021651c3a","order":22},{"adult":false,"gender":2,"id":6326,"known_for_department":"Acting","name":"Pat Skipper","original_name":"Pat Skipper","popularity":4.18,"profile_path":"/83kKXFGLe1GDXc1lau63gD5W9uF.jpg","cast_id":109,"character":"Hitman","credit_id":"5ee492390cb3350022bc3881","order":23},{"adult":false,"gender":2,"id":120560,"known_for_department":"Acting","name":"Jim Piddock","original_name":"Jim Piddock","popularity":5.327,"profile_path":"/kcEcWZVNkF1h9LQr5N60vViVZxu.jpg","cast_id":110,"character":"Consulate Envoy","credit_id":"5ee4926f0cb3350022bc38b9","order":24},{"adult":false,"gender":2,"id":169292,"known_for_department":"Acting","name":"David Marciano","original_name":"David Marciano","popularity":3.968,"profile_path":"/dqgkHEuY3mgWI3AiBK99YN9srSt.jpg","cast_id":111,"character":"Cop #1","credit_id":"5ee49290a217c00022d111b6","order":25},{"adult":false,"gender":2,"id":93925,"known_for_department":"Acting","name":"Tommy Hinkley","original_name":"Tommy Hinkley","popularity":3.994,"profile_path":"/lNN8KIup3A4y06sl5gJKApYHmQZ.jpg","cast_id":112,"character":"Cop #2","credit_id":"5ee492abcb71b8001cb3b5dd","order":26},{"adult":false,"gender":2,"id":2676859,"known_for_department":"Acting","name":"Lionel Douglass","original_name":"Lionel Douglass","popularity":0.694,"profile_path":null,"cast_id":113,"character":"Officer Friesen","credit_id":"5ee492d197eab4001fe37ac3","order":27},{"adult":false,"gender":2,"id":1233872,"known_for_department":"Acting","name":"James Oliver","original_name":"James Oliver","popularity":0.84,"profile_path":"/urTMOFzXSVvcZFnpa19Jquaj2hz.jpg","cast_id":114,"character":"Officer Moss","credit_id":"5ee492f2cb71b8001cb3b63f","order":28},{"adult":false,"gender":1,"id":153395,"known_for_department":"Acting","name":"Marian Collier","original_name":"Marian Collier","popularity":1.882,"profile_path":"/ohSTBTqC4XRqrQZdfGBP7p3pxFH.jpg","cast_id":115,"character":"Poolside Card Player","credit_id":"5ee49316cb71b8001db3afbd","order":29},{"adult":false,"gender":2,"id":95805,"known_for_department":"Acting","name":"Norman D. Wilson","original_name":"Norman D. Wilson","popularity":1.813,"profile_path":"/gHQ3ROReJWHijUtLNhF1q8TkEa4.jpg","cast_id":119,"character":"Man in Squad Room","credit_id":"6101b6d31b7294002f6d28a3","order":30}],"crew":[{"adult":false,"gender":0,"id":375,"known_for_department":"Sound","name":"Bub Asman","original_name":"Bub Asman","popularity":1.62,"profile_path":null,"credit_id":"59b5307a92514103f6000ff1","department":"Sound","job":"Sound Editor"},{"adult":false,"gender":2,"id":737,"known_for_department":"Writing","name":"Jeffrey Boam","original_name":"Jeffrey Boam","popularity":4.085,"profile_path":null,"credit_id":"52fe4291c3a36847f8028bc9","department":"Writing","job":"Screenplay"},{"adult":false,"gender":2,"id":1091,"known_for_department":"Production","name":"Joel Silver","original_name":"Joel Silver","popularity":2.257,"profile_path":"/5YWxIdEql8yyGWIcF1X3QPQ40u6.jpg","credit_id":"52fe4291c3a36847f8028bd5","department":"Production","job":"Producer"},{"adult":false,"gender":2,"id":1108,"known_for_department":"Writing","name":"Shane Black","original_name":"Shane Black","popularity":5.527,"profile_path":"/fafBg8LjtQqsXyFg8ZgW7DHQXKt.jpg","credit_id":"5580a365925141613c0001b0","department":"Writing","job":"Story"},{"adult":false,"gender":2,"id":2523,"known_for_department":"Editing","name":"Stuart Baird","original_name":"Stuart Baird","popularity":3.703,"profile_path":"/rSKMlgfJ1m2xZcsxHUV0hvYc9Eh.jpg","credit_id":"52fe4291c3a36847f8028bff","department":"Editing","job":"Editor"},{"adult":false,"gender":2,"id":2585,"known_for_department":"Acting","name":"Eric Clapton","original_name":"Eric Clapton","popularity":4.054,"profile_path":"/xAt8X2SzU4gghOyf8xjPPknHNyv.jpg","credit_id":"52fe4291c3a36847f8028be7","department":"Sound","job":"Original Music Composer"},{"adult":false,"gender":1,"id":3806,"known_for_department":"Production","name":"Marion Dougherty","original_name":"Marion Dougherty","popularity":1.388,"profile_path":null,"credit_id":"52fe4291c3a36847f8028c05","department":"Production","job":"Casting"},{"adult":false,"gender":1,"id":4694,"known_for_department":"Production","name":"Lisa Cogswell","original_name":"Lisa Cogswell","popularity":1.932,"profile_path":null,"credit_id":"5ca52aedc3a3685abe0d2d0d","department":"Production","job":"Production Secretary"},{"adult":false,"gender":2,"id":4698,"known_for_department":"Production","name":"Gregory Manson","original_name":"Gregory Manson","popularity":0.84,"profile_path":null,"credit_id":"59b52fb5c3a36878b9000635","department":"Production","job":"Production Accountant"},{"adult":false,"gender":2,"id":4699,"known_for_department":"Production","name":"Steve Perry","original_name":"Steve Perry","popularity":2.304,"profile_path":null,"credit_id":"59b52efe9251410403000e2e","department":"Production","job":"Unit Production Manager"},{"adult":false,"gender":2,"id":4699,"known_for_department":"Production","name":"Steve Perry","original_name":"Steve Perry","popularity":2.304,"profile_path":null,"credit_id":"5580a3b492514144980002a2","department":"Production","job":"Co-Producer"},{"adult":false,"gender":2,"id":4699,"known_for_department":"Production","name":"Steve Perry","original_name":"Steve Perry","popularity":2.304,"profile_path":null,"credit_id":"5ca4fef9c3a3685ab60ce7ee","department":"Directing","job":"Second Unit Director"},{"adult":false,"gender":2,"id":5582,"known_for_department":"Camera","name":"Stephen Goldblatt","original_name":"Stephen Goldblatt","popularity":1.96,"profile_path":null,"credit_id":"52fe4291c3a36847f8028bf9","department":"Camera","job":"Director of Photography"},{"adult":false,"gender":2,"id":7187,"known_for_department":"Directing","name":"Richard Donner","original_name":"Richard Donner","popularity":5.175,"profile_path":"/wjRecQiVLUAm6jwyT5craxhg3lD.jpg","credit_id":"52fe4291c3a36847f8028bbd","department":"Directing","job":"Director"},{"adult":false,"gender":2,"id":7187,"known_for_department":"Directing","name":"Richard Donner","original_name":"Richard Donner","popularity":5.175,"profile_path":"/wjRecQiVLUAm6jwyT5craxhg3lD.jpg","credit_id":"52fe4291c3a36847f8028bcf","department":"Production","job":"Producer"},{"adult":false,"gender":2,"id":8867,"known_for_department":"Art","name":"Marvin March","original_name":"Marvin March","popularity":1.71,"profile_path":null,"credit_id":"52fe4291c3a36847f8028c1d","department":"Art","job":"Set Decoration"},{"adult":false,"gender":2,"id":13304,"known_for_department":"Art","name":"J. Michael Riva","original_name":"J. Michael Riva","popularity":2.744,"profile_path":"/54ds2S5EdGOG8ynqQyYm344vGib.jpg","credit_id":"52fe4291c3a36847f8028c11","department":"Art","job":"Production Design"},{"adult":false,"gender":2,"id":7714,"known_for_department":"Sound","name":"Michael Kamen","original_name":"Michael Kamen","popularity":1.96,"profile_path":"/e1n50csgg8v4vtwVNwEq5O45Wqw.jpg","credit_id":"52fe4291c3a36847f8028bed","department":"Sound","job":"Original Music Composer"},{"adult":false,"gender":2,"id":7714,"known_for_department":"Sound","name":"Michael Kamen","original_name":"Michael Kamen","popularity":1.96,"profile_path":"/e1n50csgg8v4vtwVNwEq5O45Wqw.jpg","credit_id":"59b530319251411394000334","department":"Sound","job":"Orchestrator"},{"adult":false,"gender":2,"id":7859,"known_for_department":"Crew","name":"Matt Sweeney","original_name":"Matt Sweeney","popularity":0.694,"profile_path":null,"credit_id":"59b52ea7c3a368787000054a","department":"Crew","job":"Special Effects Coordinator"},{"adult":false,"gender":1,"id":11658,"known_for_department":"Production","name":"Gail Levin","original_name":"Gail Levin","popularity":1.4,"profile_path":null,"credit_id":"52fe4291c3a36847f8028c0b","department":"Production","job":"Casting"},{"adult":false,"gender":2,"id":12849,"known_for_department":"Costume \u0026 Make-Up","name":"Barry Francis Delaney","original_name":"Barry Francis Delaney","popularity":1.473,"profile_path":null,"credit_id":"59b52d76925141139400002a","department":"Costume \u0026 Make-Up","job":"Costume Supervisor"},{"adult":false,"gender":1,"id":14337,"known_for_department":"Production","name":"Jennie Lew Tugend","original_name":"Jennie Lew Tugend","popularity":1.96,"profile_path":null,"credit_id":"5580a3a592514144aa0002f9","department":"Production","job":"Co-Producer"},{"adult":false,"gender":0,"id":10810,"known_for_department":"Production","name":"Peter Frankfurt","original_name":"Peter Frankfurt","popularity":1.62,"profile_path":null,"credit_id":"5580a39b92514144a700027d","department":"Production","job":"Associate Producer"},{"adult":false,"gender":2,"id":14322,"known_for_department":"Acting","name":"David Sanborn","original_name":"David Sanborn","popularity":0.84,"profile_path":null,"credit_id":"52fe4291c3a36847f8028bf3","department":"Sound","job":"Original Music Composer"},{"adult":false,"gender":2,"id":14323,"known_for_department":"Art","name":"Richard Berger","original_name":"Richard Berger","popularity":0.84,"profile_path":null,"credit_id":"52fe4291c3a36847f8028c17","department":"Art","job":"Art Direction"},{"adult":false,"gender":0,"id":14336,"known_for_department":"Crew","name":"Michael Klastorin","original_name":"Michael Klastorin","popularity":1.96,"profile_path":null,"credit_id":"59b52f1ec3a36873cc0008cd","department":"Crew","job":"Unit Publicist"},{"adult":false,"gender":2,"id":16563,"known_for_department":"Crew","name":"Charles A. Tamburro","original_name":"Charles A. Tamburro","popularity":2.247,"profile_path":"/iCygZNkwUc2wSEIT58qUpiIkIC.jpg","credit_id":"5ca52a7d0e0a260158a96e8c","department":"Crew","job":"Aerial Coordinator"},{"adult":false,"gender":2,"id":18889,"known_for_department":"Crew","name":"Mic Rodgers","original_name":"Mic Rodgers","popularity":2.542,"profile_path":"/zGhWhiTfzeSzfKt9kK4Bk6ZS0xn.jpg","credit_id":"5ca52a1cc3a3685ab30d3ea2","department":"Crew","job":"Stunt Double"},{"adult":false,"gender":1,"id":21795,"known_for_department":"Art","name":"Virginia Randolph-Weaver","original_name":"Virginia Randolph-Weaver","popularity":1.214,"profile_path":null,"credit_id":"59b51740c3a36816a50019d6","department":"Art","job":"Art Direction"},{"adult":false,"gender":0,"id":4727,"known_for_department":"Art","name":"Dianne Wager","original_name":"Dianne Wager","popularity":1.4,"profile_path":null,"credit_id":"59b52c69c3a36873cc0005c9","department":"Art","job":"Set Designer"},{"adult":false,"gender":2,"id":55245,"known_for_department":"Camera","name":"John R. Shannon","original_name":"John R. Shannon","popularity":1.96,"profile_path":null,"credit_id":"59b52d559251410bc4000693","department":"Camera","job":"Still Photographer"},{"adult":false,"gender":2,"id":57347,"known_for_department":"Production","name":"Terry Miller","original_name":"Terry Miller","popularity":0.731,"profile_path":null,"credit_id":"59b52f4ec3a36878b90005cf","department":"Directing","job":"First Assistant Director"},{"adult":false,"gender":0,"id":65619,"known_for_department":"Writing","name":"Warren Murphy","original_name":"Warren Murphy","popularity":1.172,"profile_path":null,"credit_id":"5580a37092514144aa0002f6","department":"Writing","job":"Story"},{"adult":false,"gender":0,"id":74790,"known_for_department":"Camera","name":"Kirk Bales","original_name":"Kirk Bales","popularity":1.4,"profile_path":null,"credit_id":"5ca52a550e0a260164a984e8","department":"Camera","job":"Second Assistant Camera"},{"adult":false,"gender":0,"id":74800,"known_for_department":"Camera","name":"Charles Saldana","original_name":"Charles Saldana","popularity":0.694,"profile_path":null,"credit_id":"59b52cacc3a36873cc000608","department":"Camera","job":"Key Grip"},{"adult":false,"gender":2,"id":91243,"known_for_department":"Crew","name":"Charlie Picerni","original_name":"Charlie Picerni","popularity":0.84,"profile_path":"/kRO5tGbhZOPnUH46keu01i5UYd.jpg","credit_id":"59b52ebc9251410bc4000858","department":"Crew","job":"Stunt Coordinator"},{"adult":false,"gender":2,"id":161787,"known_for_department":"Crew","name":"Dick Ziker","original_name":"Dick Ziker","popularity":4.372,"profile_path":"/28dO89lvvZS6ZOw5Rpusygfbwbu.jpg","credit_id":"60367c2ae627190041286de3","department":"Crew","job":"Stunts"},{"adult":false,"gender":2,"id":933949,"known_for_department":"Directing","name":"Geary McLeod","original_name":"Geary McLeod","popularity":2.089,"profile_path":null,"credit_id":"59b52c8ec3a36871b80006d0","department":"Camera","job":"First Assistant Camera"},{"adult":false,"gender":2,"id":1086456,"known_for_department":"Art","name":"David J. Negron Jr.","original_name":"David J. Negron Jr.","popularity":0.84,"profile_path":null,"credit_id":"59b530cc9251417fef001266","department":"Writing","job":"Storyboard"},{"adult":false,"gender":2,"id":1116937,"known_for_department":"Sound","name":"John Roesch","original_name":"John Roesch","popularity":0.84,"profile_path":null,"credit_id":"5ca4ff249251412dff1eb8e9","department":"Sound","job":"Foley Artist"},{"adult":false,"gender":2,"id":1216735,"known_for_department":"Directing","name":"Paul Abascal","original_name":"Paul Abascal","popularity":1.473,"profile_path":null,"credit_id":"59b52d8e9251410f920003ee","department":"Costume \u0026 Make-Up","job":"Hairstylist"},{"adult":false,"gender":0,"id":1231182,"known_for_department":"Production","name":"David Israel","original_name":"David Israel","popularity":1.22,"profile_path":null,"credit_id":"59b52f949251410f92000636","department":"Production","job":"Location Manager"},{"adult":false,"gender":0,"id":1315669,"known_for_department":"Acting","name":"Gilbert O. Parra","original_name":"Gilbert O. Parra","popularity":1.62,"profile_path":null,"credit_id":"5ca52affc3a3685abe0d2d52","department":"Crew","job":"Technical Advisor"},{"adult":false,"gender":2,"id":1316296,"known_for_department":"Costume \u0026 Make-Up","name":"Scott H. Eddo","original_name":"Scott H. Eddo","popularity":1.313,"profile_path":null,"credit_id":"59b52daf9251410f14000447","department":"Costume \u0026 Make-Up","job":"Makeup Artist"},{"adult":false,"gender":0,"id":1367672,"known_for_department":"Lighting","name":"Bob E. Krattiger","original_name":"Bob E. Krattiger","popularity":1.96,"profile_path":null,"credit_id":"5ca52ac8c3a3685ac20d38f3","department":"Lighting","job":"Assistant Chief Lighting Technician"},{"adult":false,"gender":0,"id":1376897,"known_for_department":"Art","name":"John Villarino","original_name":"John Villarino","popularity":2.412,"profile_path":null,"credit_id":"59b52bfd9251410bc4000506","department":"Art","job":"Construction Coordinator"},{"adult":false,"gender":2,"id":1378229,"known_for_department":"Sound","name":"Marvin E. Lewis","original_name":"Marvin E. Lewis","popularity":1.96,"profile_path":null,"credit_id":"59b52fce92514103f6000f56","department":"Sound","job":"Boom Operator"},{"adult":false,"gender":2,"id":1395255,"known_for_department":"Sound","name":"Greg Orloff","original_name":"Greg Orloff","popularity":1.025,"profile_path":null,"credit_id":"5ca4ff390e0a260160a9311f","department":"Sound","job":"Foley Mixer"},{"adult":false,"gender":0,"id":1398880,"known_for_department":"Crew","name":"Craig Lietzke","original_name":"Craig Lietzke","popularity":1.96,"profile_path":null,"credit_id":"5ca52a35c3a3685ab60d3a7d","department":"Crew","job":"Stunt Driver"},{"adult":false,"gender":2,"id":1399145,"known_for_department":"Lighting","name":"Gary Holt","original_name":"Gary Holt","popularity":0.828,"profile_path":null,"credit_id":"5ca52ad9c3a3685ab30d3ff8","department":"Lighting","job":"Chief Lighting Technician"},{"adult":false,"gender":0,"id":1400853,"known_for_department":"Art","name":"Mike Villarino","original_name":"Mike Villarino","popularity":1.932,"profile_path":null,"credit_id":"59b52c2bc3a36878b9000276","department":"Art","job":"Construction Foreman"},{"adult":false,"gender":2,"id":1401253,"known_for_department":"Art","name":"Erik L. Nelson","original_name":"Erik L. Nelson","popularity":2.188,"profile_path":null,"credit_id":"59b52e469251410f14000505","department":"Art","job":"Property Master"},{"adult":false,"gender":0,"id":1401259,"known_for_department":"Sound","name":"Robert G. Henderson","original_name":"Robert G. Henderson","popularity":2.084,"profile_path":null,"credit_id":"59b530ab9251410f9200074f","department":"Sound","job":"Supervising Sound Editor"},{"adult":false,"gender":2,"id":1401265,"known_for_department":"Camera","name":"Frank M. Holgate","original_name":"Frank M. Holgate","popularity":1.012,"profile_path":null,"credit_id":"59b52cda9251410f92000306","department":"Camera","job":"Aerial Camera"},{"adult":false,"gender":0,"id":1404761,"known_for_department":"Art","name":"Sherman Labby","original_name":"Sherman Labby","popularity":0.828,"profile_path":null,"credit_id":"59b52c4cc3a3686a1a000a7f","department":"Art","job":"Production Illustrator"},{"adult":false,"gender":2,"id":1417685,"known_for_department":"Crew","name":"Gregory J. Barnett","original_name":"Gregory J. Barnett","popularity":1.96,"profile_path":"/97Gns4ZXSHaVcpMwJSUjH3etjCx.jpg","credit_id":"5b786170925141294c014412","department":"Crew","job":"Stunts"},{"adult":false,"gender":2,"id":1422061,"known_for_department":"Sound","name":"James Simcik","original_name":"James Simcik","popularity":1.96,"profile_path":null,"credit_id":"5ca4ff12c3a3685ab30cf191","department":"Sound","job":"ADR Editor"},{"adult":false,"gender":1,"id":1424126,"known_for_department":"Sound","name":"Carolyn Tapp","original_name":"Carolyn Tapp","popularity":1.96,"profile_path":null,"credit_id":"5ca529e1c3a3685ac20d37d8","department":"Sound","job":"Foley Recordist"},{"adult":false,"gender":2,"id":1424136,"known_for_department":"Crew","name":"Jack Lietzke","original_name":"Jack Lietzke","popularity":1.22,"profile_path":null,"credit_id":"59b52ee9c3a368699d000e23","department":"Crew","job":"Transportation Coordinator"},{"adult":false,"gender":1,"id":1456359,"known_for_department":"Crew","name":"Julie Adams","original_name":"Julie Adams","popularity":1.96,"profile_path":null,"credit_id":"59b52de29251410f92000447","department":"Crew","job":"Dialect Coach"},{"adult":false,"gender":2,"id":1458533,"known_for_department":"Sound","name":"Christopher Brooks","original_name":"Christopher Brooks","popularity":1.62,"profile_path":null,"credit_id":"59b53016c3a368699d000f6d","department":"Sound","job":"Music Editor"},{"adult":false,"gender":0,"id":1532615,"known_for_department":"Art","name":"Dan Pemberton","original_name":"Dan Pemberton","popularity":1.214,"profile_path":null,"credit_id":"59b52e309251410f140004ea","department":"Crew","job":"Propmaker"},{"adult":false,"gender":1,"id":1544695,"known_for_department":"Directing","name":"Nancy Hansen","original_name":"Nancy Hansen","popularity":0.84,"profile_path":null,"credit_id":"609b9becc51acd003fb758bc","department":"Directing","job":"Script Supervisor"},{"adult":false,"gender":2,"id":1546115,"known_for_department":"Sound","name":"Willie D. Burton","original_name":"Willie D. Burton","popularity":2.18,"profile_path":null,"credit_id":"59b53056c3a3686a1a000f14","department":"Sound","job":"Production Sound Mixer"},{"adult":false,"gender":0,"id":1586929,"known_for_department":"Crew","name":"Michael Denering","original_name":"Michael Denering","popularity":1.528,"profile_path":null,"credit_id":"59b52e65c3a36871d7000913","department":"Crew","job":"Scenic Artist"},{"adult":false,"gender":2,"id":1647993,"known_for_department":"Directing","name":"Albert Cho","original_name":"Albert Cho","popularity":1.22,"profile_path":null,"credit_id":"5ca4fecc0e0a26015ca93e2c","department":"Directing","job":"Second Second Assistant Director"},{"adult":false,"gender":1,"id":1661873,"known_for_department":"Production","name":"Kristin Dewey","original_name":"Kristin Dewey","popularity":0.694,"profile_path":null,"credit_id":"5ca52a699251412df61ef523","department":"Production","job":"Assistant Location Manager"},{"adult":false,"gender":0,"id":1728443,"known_for_department":"Sound","name":"Jay Engel","original_name":"Jay Engel","popularity":1.708,"profile_path":null,"credit_id":"5ca52a0b0e0a260164a984b2","department":"Sound","job":"Supervising ADR Editor"},{"adult":false,"gender":2,"id":1849260,"known_for_department":"Acting","name":"Michael Alan Kahn","original_name":"Michael Alan Kahn","popularity":0.98,"profile_path":null,"credit_id":"611277a8d05a03007f53ad54","department":"Directing","job":"Second Assistant Director"},{"adult":false,"gender":0,"id":1885270,"known_for_department":"Crew","name":"Frank DeMichelis","original_name":"Frank DeMichelis","popularity":0.828,"profile_path":null,"credit_id":"59b52dd29251411394000097","department":"Crew","job":"Craft Service"},{"adult":false,"gender":0,"id":1885271,"known_for_department":"Crew","name":"Amy Jackson","original_name":"Amy Jackson","popularity":0.6,"profile_path":null,"credit_id":"59b52e229251410403000d3e","department":"Crew","job":"Production Office Assistant"},{"adult":false,"gender":0,"id":1885273,"known_for_department":"Crew","name":"Richmond G. Cogswell","original_name":"Richmond G. Cogswell","popularity":0.84,"profile_path":null,"credit_id":"59b52f3f9251410403000e6f","department":"Crew","job":"Video Assist Operator"},{"adult":false,"gender":0,"id":1885274,"known_for_department":"Sound","name":"Darrin Martin","original_name":"Darrin Martin","popularity":0.84,"profile_path":null,"credit_id":"59b52fe692514103f6000f7d","department":"Sound","job":"Assistant Sound Editor"},{"adult":false,"gender":2,"id":1900639,"known_for_department":"Sound","name":"Stephen McLaughlin","original_name":"Stephen McLaughlin","popularity":0.84,"profile_path":"/q7WO4q0OoJPmyN15NJAO8fh5q0p.jpg","credit_id":"5ba64276c3a3680e6800af7a","department":"Sound","job":"Music Producer"},{"adult":false,"gender":0,"id":2196547,"known_for_department":"Camera","name":"Danny Falkengren","original_name":"Danny Falkengren","popularity":0.84,"profile_path":null,"credit_id":"5ca52a450e0a26015ea97dd9","department":"Camera","job":"Dolly Grip"},{"adult":false,"gender":0,"id":2280344,"known_for_department":"Costume \u0026 Make-Up","name":"Vicky Snow","original_name":"Vicky Snow","popularity":0.6,"profile_path":null,"credit_id":"5ca4fead9251412df61ea279","department":"Costume \u0026 Make-Up","job":"Costumer"},{"adult":false,"gender":0,"id":2280345,"known_for_department":"Art","name":"Gary F. Kieldrup","original_name":"Gary F. Kieldrup","popularity":0.694,"profile_path":null,"credit_id":"5ca4ff07c3a3685ab60ce7f9","department":"Art","job":"Assistant Property Master"}]}